example_package_xuexiang/.gitignore
example_package_xuexiang/.python-version
example_package_xuexiang/__init__.py
example_package_xuexiang/example.py
example_package_xuexiang-0.1.0.dist-info/METADATA
example_package_xuexiang-0.1.0.dist-info/WHEEL
example_package_xuexiang-0.1.0.dist-info/licenses/LICENSE.txt
example_package_xuexiang-0.1.0.dist-info/RECORD
