Metadata-Version: 2.4
Name: example-package-xuexiang
Version: 0.1.0
Summary: my add package
License-Expression: MIT
License-File: LICENSE.txt
Requires-Python: >=3.12
